[{"id":60521,"userId":8,"deviceId":8,"time":"2019-02-23 00:00:00","consume":0,"isAtHome":"U","isAnomalous":0},
{"id":60522,"userId":8,"deviceId":8,"time":"2019-02-23 01:00:00","consume":0,"isAtHome":"U","isAnomalous":0},
{"id":60523,"userId":8,"deviceId":8,"time":"2019-02-23 02:00:00","consume":0,"isAtHome":"U","isAnomalous":0},
{"id":60524,"userId":8,"deviceId":8,"time":"2019-02-23 03:00:00","consume":0,"isAtHome":"U","isAnomalous":0},
{"id":60525,"userId":8,"deviceId":8,"time":"2019-02-23 04:00:00","consume":0,"isAtHome":"U","isAnomalous":0},
{"id":60526,"userId":8,"deviceId":8,"time":"2019-02-23 05:00:00","consume":0,"isAtHome":"U","isAnomalous":0},
{"id":60527,"userId":8,"deviceId":8,"time":"2019-02-23 06:00:00","consume":0,"isAtHome":"U","isAnomalous":0},
{"id":60528,"userId":8,"deviceId":8,"time":"2019-02-23 07:00:00","consume":0,"isAtHome":"U","isAnomalous":0},
{"id":60529,"userId":8,"deviceId":8,"time":"2019-02-23 08:00:00","consume":100,"isAtHome":"N","isAnomalous":1},
{"id":60530,"userId":8,"deviceId":8,"time":"2019-02-23 09:00:00","consume":0,"isAtHome":"N","isAnomalous":0},
{"id":60531,"userId":8,"deviceId":8,"time":"2019-02-23 10:00:00","consume":0,"isAtHome":"N","isAnomalous":0},
{"id":60532,"userId":8,"deviceId":8,"time":"2019-02-23 11:00:00","consume":0,"isAtHome":"N","isAnomalous":0},
{"id":60533,"userId":8,"deviceId":8,"time":"2019-02-23 12:00:00","consume":0,"isAtHome":"N","isAnomalous":0},
{"id":60534,"userId":8,"deviceId":8,"time":"2019-02-23 13:00:00","consume":0,"isAtHome":"N","isAnomalous":0},
{"id":60535,"userId":8,"deviceId":8,"time":"2019-02-23 14:00:00","consume":0,"isAtHome":"N","isAnomalous":0},
{"id":60536,"userId":8,"deviceId":8,"time":"2019-02-23 15:00:00","consume":0,"isAtHome":"N","isAnomalous":0},
{"id":60537,"userId":8,"deviceId":8,"time":"2019-02-23 16:00:00","consume":0,"isAtHome":"N","isAnomalous":0},
{"id":60538,"userId":8,"deviceId":8,"time":"2019-02-23 17:00:00","consume":0,"isAtHome":"N","isAnomalous":0},
{"id":60539,"userId":8,"deviceId":8,"time":"2019-02-23 18:00:00","consume":0,"isAtHome":"N","isAnomalous":0},
{"id":60540,"userId":8,"deviceId":8,"time":"2019-02-23 19:00:00","consume":0,"isAtHome":"N","isAnomalous":0},
{"id":60541,"userId":8,"deviceId":8,"time":"2019-02-23 20:00:00","consume":0,"isAtHome":"N","isAnomalous":0},
{"id":60542,"userId":8,"deviceId":8,"time":"2019-02-23 21:00:00","consume":6,"isAtHome":"U","isAnomalous":0},
{"id":60543,"userId":8,"deviceId":8,"time":"2019-02-23 22:00:00","consume":6,"isAtHome":"U","isAnomalous":0},
{"id":60544,"userId":8,"deviceId":8,"time":"2019-02-23 23:00:00","consume":4,"isAtHome":"U","isAnomalous":0},
{"id":60545,"userId":8,"deviceId":8,"time":"2019-02-24 00:00:00","consume":0,"isAtHome":"U","isAnomalous":0},
{"id":60546,"userId":8,"deviceId":8,"time":"2019-02-24 01:00:00","consume":0,"isAtHome":"U","isAnomalous":0},
{"id":60547,"userId":8,"deviceId":8,"time":"2019-02-24 02:00:00","consume":0,"isAtHome":"U","isAnomalous":0},
{"id":60548,"userId":8,"deviceId":8,"time":"2019-02-24 03:00:00","consume":0,"isAtHome":"U","isAnomalous":0},
{"id":60549,"userId":8,"deviceId":8,"time":"2019-02-24 04:00:00","consume":0,"isAtHome":"U","isAnomalous":0},
{"id":60550,"userId":8,"deviceId":8,"time":"2019-02-24 05:00:00","consume":0,"isAtHome":"U","isAnomalous":0},
{"id":60551,"userId":8,"deviceId":8,"time":"2019-02-24 06:00:00","consume":0,"isAtHome":"U","isAnomalous":0},
{"id":60552,"userId":8,"deviceId":8,"time":"2019-02-24 07:00:00","consume":1,"isAtHome":"U","isAnomalous":0},
{"id":60553,"userId":8,"deviceId":8,"time":"2019-02-24 08:00:00","consume":150,"isAtHome":"U","isAnomalous":1},
{"id":60554,"userId":8,"deviceId":8,"time":"2019-02-24 09:00:00","consume":0,"isAtHome":"U","isAnomalous":0},
{"id":60555,"userId":8,"deviceId":8,"time":"2019-02-24 10:00:00","consume":0,"isAtHome":"U","isAnomalous":0},
{"id":60556,"userId":8,"deviceId":8,"time":"2019-02-24 11:00:00","consume":0,"isAtHome":"U","isAnomalous":0},
{"id":60557,"userId":8,"deviceId":8,"time":"2019-02-24 12:00:00","consume":0,"isAtHome":"U","isAnomalous":0},
{"id":60558,"userId":8,"deviceId":8,"time":"2019-02-24 13:00:00","consume":0,"isAtHome":"U","isAnomalous":0},
{"id":60559,"userId":8,"deviceId":8,"time":"2019-02-24 14:00:00","consume":0,"isAtHome":"U","isAnomalous":0},
{"id":60560,"userId":8,"deviceId":8,"time":"2019-02-24 15:00:00","consume":0,"isAtHome":"U","isAnomalous":0},
{"id":60561,"userId":8,"deviceId":8,"time":"2019-02-24 16:00:00","consume":0,"isAtHome":"U","isAnomalous":0},
{"id":60562,"userId":8,"deviceId":8,"time":"2019-02-24 17:00:00","consume":0,"isAtHome":"U","isAnomalous":0},
{"id":60563,"userId":8,"deviceId":8,"time":"2019-02-24 18:00:00","consume":0,"isAtHome":"U","isAnomalous":0},
{"id":60564,"userId":8,"deviceId":8,"time":"2019-02-24 19:00:00","consume":5,"isAtHome":"U","isAnomalous":0},
{"id":60565,"userId":8,"deviceId":8,"time":"2019-02-24 20:00:00","consume":0,"isAtHome":"U","isAnomalous":0},
{"id":60566,"userId":8,"deviceId":8,"time":"2019-02-24 21:00:00","consume":1,"isAtHome":"U","isAnomalous":0},
{"id":60567,"userId":8,"deviceId":8,"time":"2019-02-24 22:00:00","consume":6,"isAtHome":"U","isAnomalous":0},
{"id":60568,"userId":8,"deviceId":8,"time":"2019-02-24 23:00:00","consume":1,"isAtHome":"U","isAnomalous":0}]